HiSTra/BoxFinder.py
HiSTra/SignalFinder.py
HiSTra/SparseMatrixDeal.py
HiSTra/__init__.py
HiSTra/hicInput.py
HiSTra/run_main.py
HiSTra/utils.py
HiSTra/deDoc/deDoc.jar
HiSTra/juice/juicer_tools_2.09.00.jar
HiSTra-1.4.0.data/scripts/HiST
HiSTra-1.4.0.dist-info/LICENSE.txt
HiSTra-1.4.0.dist-info/METADATA
HiSTra-1.4.0.dist-info/WHEEL
HiSTra-1.4.0.dist-info/top_level.txt
HiSTra-1.4.0.dist-info/RECORD
