Metadata-Version: 2.1
Name: HiSTra
Version: 1.4.0
Summary: Spectral translocation detection of HiC matrices.
Home-page: https://github.com/dtzxyangq/HiSTra
Author: Q.Yang
Author-email: dtzxyangq@foxmail.com
License: MIT
Keywords: HiC genome structure variation translocation
Classifier: Programming Language :: Python :: 3
Classifier: License :: OSI Approved :: MIT License
Classifier: Operating System :: OS Independent
Requires-Python: >=3.6
License-File: LICENSE.txt
Requires-Dist: numpy
Requires-Dist: scipy
Requires-Dist: pandas<=1.3.5
Requires-Dist: matplotlib
Requires-Dist: seaborn
Requires-Dist: cooler<=0.8.11
